pyslurm_computecanada/__init__.py
pyslurm_computecanada/pyslurm.py
pyslurm_computecanada-0.1.dist-info/LICENSE
pyslurm_computecanada-0.1.dist-info/METADATA
pyslurm_computecanada-0.1.dist-info/WHEEL
pyslurm_computecanada-0.1.dist-info/top_level.txt
pyslurm_computecanada-0.1.dist-info/RECORD
