Metadata-Version: 2.1
Name: pyslurm-computecanada
Version: 0.1
Summary: wrapper for slurm job manager on compute canada clusters
Home-page: UNKNOWN
Author: sebastien Leblanc
Author-email: sebastien.leblanc5@usherbrooke.ca
License: MIT
Platform: UNKNOWN
Requires-Python: >=3.6
